zino/__init__.py
zino/compat.py
zino/debug.py
zino/events.py
zino/flaps.py
zino/getuptime.py
zino/getyellowalarms.py
zino/job_tracker.py
zino/oid.py
zino/planned_maintenance.py
zino/polltest.py
zino/scheduler.py
zino/state.py
zino/statemodels.py
zino/time.py
zino/traptest.py
zino/utils.py
zino/version.py
zino/zino.py
zino/api/__init__.py
zino/api/auth.py
zino/api/legacy.py
zino/api/notify.py
zino/api/server.py
zino/config/__init__.py
zino/config/models.py
zino/config/polldevs.py
zino/snmp/__init__.py
zino/snmp/agent.py
zino/snmp/base.py
zino/snmp/netsnmpy_backend.py
zino/snmp/pysnmp_backend.py
zino/snmp/mibdumps/BFD-STD-MIB.py
zino/snmp/mibdumps/BFD-TC-STD-MIB.py
zino/snmp/mibdumps/BGP4-MIB.py
zino/snmp/mibdumps/BGP4-V2-MIB-JUNIPER.py
zino/snmp/mibdumps/CISCO-BGP4-MIB.py
zino/snmp/mibdumps/CISCO-CONFIG-MAN-MIB.py
zino/snmp/mibdumps/CISCO-IETF-BFD-MIB.py
zino/snmp/mibdumps/CISCO-PIM-MIB.py
zino/snmp/mibdumps/CISCO-SMI.py
zino/snmp/mibdumps/CISCOTRAP-MIB.py
zino/snmp/mibdumps/DIFFSERV-DSCP-TC.py
zino/snmp/mibdumps/DIFFSERV-MIB.py
zino/snmp/mibdumps/IANA-BFD-TC-STD-MIB.py
zino/snmp/mibdumps/IANA-RTPROTO-MIB.py
zino/snmp/mibdumps/IANAifType-MIB.py
zino/snmp/mibdumps/IF-MIB.py
zino/snmp/mibdumps/INET-ADDRESS-MIB.py
zino/snmp/mibdumps/INTEGRATED-SERVICES-MIB.py
zino/snmp/mibdumps/IP-MIB.py
zino/snmp/mibdumps/IPMROUTE-STD-MIB.py
zino/snmp/mibdumps/JUNIPER-ALARM-MIB.py
zino/snmp/mibdumps/JUNIPER-BFD-MIB.py
zino/snmp/mibdumps/JUNIPER-EXPERIMENT-MIB.py
zino/snmp/mibdumps/JUNIPER-SMI.py
zino/snmp/mibdumps/OLD-CISCO-INTERFACES-MIB.py
zino/snmp/mibdumps/OLD-CISCO-SYSTEM-MIB.py
zino/snmp/mibdumps/OLD-CISCO-TCP-MIB.py
zino/snmp/mibdumps/OLD-CISCO-TS-MIB.py
zino/snmp/mibdumps/OSPF-MIB.py
zino/snmp/mibdumps/OSPF-TRAP-MIB.py
zino/snmp/mibdumps/PIM-MIB.py
zino/snmp/mibdumps/TCP-MIB.py
zino/snmp/mibdumps/UNINETT-SMI.py
zino/snmp/mibdumps/ZINO-MIB.py
zino/snmp/mibs/BFD-STD-MIB
zino/snmp/mibs/BFD-TC-STD-MIB
zino/snmp/mibs/BGP4-MIB
zino/snmp/mibs/BGP4-V2-MIB-JUNIPER
zino-2.3.4.dist-info/licenses/AUTHORS.md
zino-2.3.4.dist-info/licenses/LICENSE
zino-2.3.4.dist-info/licenses/NOTICE
zino-2.3.4.dist-info/METADATA
zino-2.3.4.dist-info/WHEEL
zino-2.3.4.dist-info/entry_points.txt
zino-2.3.4.dist-info/top_level.txt
zino-2.3.4.dist-info/RECORD
