Metadata-Version: 2.4
Name: Zino
Version: 2.3.4
Summary: Robust network management system for large backbone networks
Author-email: Sikt - Norwegian Agency for Shared Services in Education and Research <kontakt@sikt.no>
License-Expression: Apache-2.0
Project-URL: Homepage, https://nordu.net/zino/
Project-URL: GitHub, https://github.com/Uninett/zino
Project-URL: Changelog, https://github.com/Uninett/zino/blob/master/CHANGELOG.md
Project-URL: Documentation, https://zino.readthedocs.io/en/latest/
Platform: any
Classifier: Intended Audience :: Information Technology
Classifier: Intended Audience :: System Administrators
Classifier: Development Status :: 5 - Production/Stable
Classifier: Programming Language :: Python :: 3 :: Only
Classifier: Programming Language :: Python :: 3.9
Classifier: Programming Language :: Python :: 3.10
Classifier: Programming Language :: Python :: 3.11
Classifier: Programming Language :: Python :: 3.12
Classifier: Topic :: System :: Networking :: Monitoring
Requires-Python: >=3.9
License-File: LICENSE
License-File: NOTICE
License-File: AUTHORS.md
Requires-Dist: apscheduler~=3.11
Requires-Dist: pydantic>=2.7.0
Requires-Dist: pysnmp~=6.2
Requires-Dist: aiodns
Requires-Dist: tomli; python_version < "3.11"
Requires-Dist: netsnmp-cffi>=0.1.4
Provides-Extra: docs
Requires-Dist: sphinx>=2.2.0; extra == "docs"
Dynamic: license-file
